{"stats":{"minecraft:used":{"minecraft:moss_carpet":2,"securitycraft:trophy_system":1,"minecraft:blue_terracotta":27,"minecraft:writable_book":31,"minecraft:chiseled_deepslate":65,"minecraft:polished_deepslate":150,"car:generator":1,"create:piston_extension_pole":29,"minecraft:smooth_quartz_slab":188,"securitycraft:keypad_trapdoor":3,"minecraft:polished_blackstone":164,"minecraft:spruce_slab":90,"minecraft:ladder":82,"minecraft:oak_sign":51,"minecraft:chest":16,"minecraft:shield":7,"create:haunted_bell":5,"minecraft:stone":397,"car:asphalt":1,"minecraft:quartz_stairs":5,"minecraft:player_head":5,"minecraft:white_shulker_box":3,"securitycraft:security_camera":10,"minecraft:iron_chestplate":9,"minecraft:debug_stick":8,"minecraft:grass":1,"create:railway_casing":47,"create:analog_lever":6,"rechiseled:dark_oak_planks_tiles":1,"create:fluid_tank":12,"minecraft:cocoa_beans":162,"create:cogwheel":42,"minecraft:carrot":1,"rechiseled:quartz_block_bordered":4,"create:creative_crate":1,"minecraft:music_disc_11":42,"minecraft:obsidian":1,"create:polished_cut_deepslate_slab":3,"easy_npc:humanoid_spawn_egg":10,"minecraft:stripped_spruce_log":12,"minecraft:milk_bucket":9,"minecraft:music_disc_relic":2,"minecraft:glass":219,"minecraft:polished_blackstone_slab":4,"minecraft:waxed_oxidized_copper":4,"securitycraft:camera_monitor":9,"create:netherite_diving_boots":1,"create:controls":7,"minecraft:stripped_dark_oak_wood":370,"minecraft:quartz_slab":42,"minecraft:grass_block":383,"minecraft:lava_bucket":4,"minecraft:coal_ore":4,"minecraft:bricks":41,"minecraft:lime_banner":12,"minecraft:quartz_pillar":34,"minecraft:quartz_block":99,"framedblocks:framed_bookshelf":1,"create:rose_quartz_lamp":2,"minecraft:red_wool":1,"minecraft:black_stained_glass_pane":181,"minecraft:lantern":15,"minecraft:birch_sapling":5,"webdisplays:server":1,"minecraft:polished_andesite_stairs":26,"minecraft:music_disc_chirp":1,"minecraft:netherite_hoe":199,"minecraft:pink_wool":5,"minecraft:repeater":7,"minecraft:stone_brick_stairs":18,"minecraft:bedrock":28,"minecraft:stone_bricks":150,"minecraft:item_frame":77,"minecraft:spruce_hanging_sign":1,"minecraft:netherite_boots":2,"car:fluid_pipe":15,"minecraft:redstone_lamp":42,"minecraft:dolphin_spawn_egg":21,"create:linked_controller":18,"minecraft:scaffolding":13,"create:steam_engine":3,"create:shaft":13,"minecraft:hay_block":74,"minecraft:written_book":25,"minecraft:infested_cracked_stone_bricks":1,"minecraft:oak_sapling":27,"securitycraft:laser_block":27,"minecraft:oxidized_cut_copper_stairs":25,"minecraft:gold_block":14,"minecraft:egg":1,"minecraft:end_stone_brick_stairs":51,"securitycraft:alarm":67,"minecraft:polished_blackstone_stairs":1,"car:tank":13,"minecraft:leather_leggings":5,"minecraft:damaged_anvil":1,"minecraft:dark_oak_stairs":61,"webdisplays:ownerthief":3,"easy_npc:easy_npc_wand":7,"minecraft:diorite":17,"minecraft:cow_spawn_egg":1,"create:netherite_diving_helmet":2,"securitycraft:door_indestructible_iron_item":12,"minecraft:gray_carpet":2,"minecraft:prismarine":52,"minecraft:dark_oak_sign":17,"minecraft:blackstone":46,"framedblocks:framed_door":8,"minecraft:oak_planks":534,"minecraft:blackstone_stairs":31,"minecraft:cactus":2,"minecraft:leather_chestplate":6,"minecraft:wooden_pickaxe":27,"minecraft:redstone_block":48,"car:oilmill":2,"create:copper_valve_handle":1,"minecraft:smooth_quartz_stairs":76,"minecraft:oak_leaves":15,"minecraft:cookie":7,"minecraft:dark_oak_trapdoor":4,"framedblocks:framed_inner_prism_corner":1,"minecraft:sand":3,"create:flywheel":1,"minecraft:light_blue_concrete":31,"create:track_station":10,"minecraft:netherite_leggings":2,"minecraft:sponge":11,"minecraft:blast_furnace":7,"minecraft:crossbow":4,"create:placard":1,"car:sign":1,"minecraft:cyan_dye":1,"minecraft:netherite_helmet":2,"minecraft:note_block":1,"minecraft:oxidized_cut_copper_slab":9,"minecraft:stone_brick_wall":17,"minecraft:gray_concrete":30,"minecraft:black_bed":1,"securitycraft:keycard_lock":4,"minecraft:end_stone":36,"minecraft:shears":539,"minecraft:lightning_rod":2,"minecraft:redstone_torch":44,"minecraft:deepslate_tiles":156,"minecraft:sticky_piston":6,"minecraft:lever":7,"minecraft:black_concrete":82,"minecraft:dark_oak_log":2,"minecraft:mangrove_door":2,"minecraft:gray_stained_glass_pane":5,"minecraft:heavy_weighted_pressure_plate":2,"minecraft:light_gray_concrete":11,"rechiseled:blackstone_polished_connecting":3,"minecraft:bread":4,"minecraft:barrier":11,"minecraft:stone_button":2,"minecraft:verdant_froglight":5,"car:dynamo":4,"create:contraption_controls":10,"securitycraft:smart_module":4,"minecraft:oak_pressure_plate":4,"create:peculiar_bell":2,"rechiseled:stone_smooth_connecting":20,"securitycraft:mine":144,"easy_npc:fairy_spawn_egg":1,"rechiseled:blackstone_tiles":38,"create:powered_toggle_latch":44,"rechiseled:blackstone_brick_paving_connecting":3,"securitycraft:motion_activated_light":2,"minecraft:stripped_oak_wood":3,"minecraft:cooked_rabbit":1,"minecraft:andesite":13,"create:framed_glass_door":31,"create:chocolate_bucket":1,"minecraft:birch_log":44,"minecraft:smooth_stone_slab":51,"car:crank":5,"minecraft:white_concrete":78,"create:steam_whistle":1,"minecraft:bone_meal":403,"create:large_cogwheel":2,"minecraft:oak_fence":28,"minecraft:oak_trapdoor":24,"create:clipboard":50,"minecraft:trident":7,"minecraft:netherite_sword":44,"minecraft:iron_bars":40,"minecraft:flint_and_steel":34,"minecraft:carved_pumpkin":1,"minecraft:armor_stand":1,"framedblocks:framed_slab":14,"create:item_vault":11,"securitycraft:keypad_chest":4,"minecraft:redstone":113,"minecraft:spruce_planks":3,"car:car_workshop_outter":25,"minecraft:ender_chest":3,"create:sticky_mechanical_piston":36,"securitycraft:remote_access_mine":10,"securitycraft:scanner_trapdoor":1,"securitycraft:keypad_door_item":5,"minecraft:brown_shulker_box":59,"car:blastfurnace":2,"minecraft:cooked_salmon":1,"minecraft:netherrack":12,"securitycraft:reinforced_iron_bars":2,"minecraft:torch":4,"minecraft:brewing_stand":1,"minecraft:end_stone_brick_wall":204,"minecraft:dirt":140,"minecraft:anvil":2,"minecraft:white_carpet":58,"minecraft:nether_quartz_ore":32,"create:redstone_contact":218,"minecraft:spruce_stairs":29,"rechiseled:basalt_bordered_polished_connecting":2,"minecraft:shulker_box":6,"minecraft:blue_concrete":3,"minecraft:polished_diorite":14,"car:fluid_extractor":26,"securitycraft:keycard_reader":2,"minecraft:dark_oak_planks":1,"webdisplays:rctrl":6,"minecraft:sea_lantern":147,"minecraft:bookshelf":1,"car:backmix_reactor":3,"minecraft:iron_block":16,"minecraft:oak_stairs":2,"create:metal_bracket":7,"minecraft:spruce_button":15,"minecraft:smooth_sandstone":5,"minecraft:smooth_quartz":1576,"rechiseled:quartz_block_small_tiles_connecting":1,"create:creative_motor":93,"minecraft:barrel":5,"minecraft:blaze_spawn_egg":1,"create:encased_chain_drive":4,"minecraft:basalt":7,"minecraft:golden_carrot":1,"minecraft:lime_concrete":31,"minecraft:black_stained_glass":129,"minecraft:cooked_beef":2,"minecraft:gray_glazed_terracotta":1,"minecraft:white_stained_glass_pane":4,"rechiseled:blackstone_brick_paving":80,"rechiseled:andesite_polished_connecting":5,"minecraft:deepslate_tile_stairs":2,"webdisplays:screencfg":41,"minecraft:enchanted_golden_apple":1,"create:content_observer":2,"minecraft:netherite_pickaxe":3108,"minecraft:cobbled_deepslate":28,"minecraft:acacia_planks":27,"minecraft:red_dye":1,"minecraft:stone_pressure_plate":1,"car:gas_station":5,"rechiseled:amethyst_block_beams":3,"minecraft:observer":7,"create:gearshift":27,"minecraft:iron_leggings":25,"create:honey_bucket":1,"webdisplays:linker":47,"minecraft:quartz_bricks":37,"minecraft:wheat_seeds":541,"minecraft:water_bucket":32,"securitycraft:projector":57,"minecraft:iron_ore":1,"minecraft:jigsaw":1,"minecraft:sandstone_stairs":2,"webdisplays:keyboard":16,"minecraft:netherite_chestplate":2,"minecraft:lime_wool":3,"create:train_door":10,"minecraft:cartography_table":3,"securitycraft:panic_button":51,"framedblocks:framed_cube":1,"minecraft:spruce_sign":9,"minecraft:leather_boots":5,"create:framed_glass_trapdoor":12,"minecraft:glow_ink_sac":30,"minecraft:green_bed":1,"securitycraft:scanner_door_item":2,"create:elevator_contact":13,"minecraft:deepslate_bricks":2,"minecraft:salmon":2,"minecraft:glow_item_frame":1,"minecraft:polished_blackstone_pressure_plate":4,"minecraft:diamond_block":14,"car:cable":45,"securitycraft:redstone_module":5,"minecraft:tnt":3,"minecraft:oak_slab":87,"minecraft:crafting_table":31,"minecraft:birch_sign":1,"minecraft:white_bed":6,"minecraft:dark_oak_fence_gate":1,"minecraft:painting":21,"minecraft:dark_oak_door":64,"create:track":65,"minecraft:flower_pot":4,"minecraft:netherite_block":43,"minecraft:oak_log":357,"minecraft:yellow_dye":2,"minecraft:piston":7,"minecraft:ender_eye":24,"minecraft:light":40,"car:split_tank":4,"minecraft:apple":14,"minecraft:command_block":17,"minecraft:oak_button":28,"minecraft:suspicious_stew":1,"minecraft:pig_spawn_egg":1,"minecraft:netherite_axe":2679,"webdisplays:redctrl":1,"minecraft:spruce_trapdoor":30,"minecraft:crimson_sign":2,"car:car_workshop":3,"minecraft:cobblestone":32,"minecraft:potion":37,"minecraft:cyan_stained_glass_pane":1,"securitycraft:cage_trap":1,"minecraft:bucket":29,"create:powered_latch":6,"minecraft:chain_command_block":15,"minecraft:glass_pane":8,"create:display_board":103,"minecraft:repeating_command_block":13,"minecraft:polished_blackstone_button":8,"minecraft:end_portal_frame":24,"create:clutch":4,"create:elevator_pulley":22,"create:redstone_link":60,"minecraft:splash_potion":3,"webdisplays:screen":339,"minecraft:jukebox":7,"minecraft:smooth_stone":28,"rechiseled:stone_smooth_large_tiles":10,"minecraft:chainmail_leggings":2},"minecraft:killed_by":{"easy_npc:skeleton":2,"minecraft:piglin":2,"minecraft:player":8,"easy_npc:humanoid":3},"minecraft:killed":{"minecraft:shulker":3,"minecraft:bee":1,"minecraft:silverfish":4,"minecraft:sheep":1,"minecraft:blaze":1,"easy_npc:humanoid":2,"minecraft:polar_bear":1},"minecraft:custom":{"minecraft:interact_with_crafting_table":2,"minecraft:open_barrel":123,"minecraft:open_shulker_box":70,"minecraft:bell_ring":69,"minecraft:eat_cake_slice":7,"minecraft:leave_game":111,"minecraft:time_since_death":50938,"minecraft:damage_resisted":351991,"minecraft:sprint_one_cm":4390811,"minecraft:damage_blocked_by_shield":210,"minecraft:drop":688,"minecraft:talked_to_villager":2,"minecraft:play_time":4915156,"minecraft:deaths":45,"minecraft:jump":31635,"minecraft:interact_with_brewingstand":22,"minecraft:walk_on_water_one_cm":63928,"minecraft:interact_with_furnace":1,"minecraft:play_record":45,"minecraft:traded_with_villager":29,"minecraft:sleep_in_bed":83,"minecraft:open_enderchest":2,"minecraft:damage_dealt":2961,"minecraft:interact_with_beacon":1,"minecraft:crouch_one_cm":279043,"minecraft:interact_with_anvil":3,"minecraft:mob_kills":14,"minecraft:climb_one_cm":37662,"minecraft:walk_one_cm":10790120,"minecraft:sneak_time":115918,"minecraft:walk_under_water_one_cm":109177,"minecraft:interact_with_lectern":19,"minecraft:interact_with_blast_furnace":40,"minecraft:total_world_time":4915156,"minecraft:tune_noteblock":19,"minecraft:pot_flower":4,"minecraft:time_since_rest":15633,"minecraft:damage_taken":11318,"minecraft:swim_one_cm":95183,"minecraft:fly_one_cm":20902773,"minecraft:open_chest":80,"minecraft:fall_one_cm":206353},"minecraft:crafted":{"minecraft:shulker_box":120,"minecraft:shulker_shell":200,"minecraft:hay_block":31,"minecraft:iron_ingot":31,"minecraft:gold_ingot":30,"minecraft:sweet_berries":32,"minecraft:cocoa_beans":32,"minecraft:diamond_block":4,"minecraft:wheat":684,"minecraft:glistering_melon_slice":18,"minecraft:coal_block":16,"minecraft:air":0,"minecraft:bread":16,"minecraft:gold_nugget":144},"minecraft:dropped":{"minecraft:spruce_sign":2,"create:belt_connector":1,"webdisplays:laserpointer":6,"minecraft:oak_log":2412,"minecraft:glass_bottle":5,"minecraft:diamond":26,"minecraft:crossbow":1,"minecraft:cookie":622,"webdisplays:craftcomp_laserdiode":2,"easy_npc:move_easy_npc":3,"minecraft:item_frame":1,"minecraft:music_disc_11":1,"securitycraft:trophy_system":1,"minecraft:black_stained_glass_pane":1,"minecraft:black_shulker_box":1,"minecraft:writable_book":6,"minecraft:gold_nugget":17,"car:crimson_body":1,"minecraft:sand":2,"securitycraft:projector":2,"minecraft:cauldron":1,"minecraft:gold_ingot":30,"car:key":2,"minecraft:diamond_block":4,"minecraft:cobbled_deepslate":129,"minecraft:netherite_sword":12,"securitycraft:taser":1,"minecraft:oak_planks":1,"minecraft:end_stone":1,"securitycraft:keypad_item":1,"minecraft:brown_shulker_box":2,"minecraft:shulker_shell":1,"minecraft:poppy":1,"minecraft:trident":4,"securitycraft:redstone_module":5,"minecraft:chest":31,"minecraft:painting":3,"framedblocks:framed_slab":1,"minecraft:scaffolding":8,"minecraft:oak_leaves":1,"minecraft:written_book":6,"minecraft:enchanted_book":4,"minecraft:iron_ingot":104,"webdisplays:minepad":29,"minecraft:netherite_pickaxe":6,"minecraft:wheat_seeds":1,"minecraft:smooth_quartz_stairs":30,"minecraft:netherite_helmet":1,"minecraft:netherite_axe":67,"minecraft:netherite_chestplate":1,"minecraft:lead":1,"minecraft:apple":20,"minecraft:command_block":1,"minecraft:coal_block":16,"create:redstone_contact":1,"minecraft:coal":1,"minecraft:stick":11,"create:clipboard":2,"minecraft:wooden_axe":1,"minecraft:potion":14,"minecraft:iron_leggings":9,"minecraft:cactus":2,"minecraft:paper":356,"minecraft:string":95,"minecraft:bucket":4,"create:raw_zinc":2,"minecraft:redstone":35,"car:canola_seeds":1,"minecraft:cocoa_beans":6,"minecraft:bowl":1,"create:linked_controller":1,"minecraft:mangrove_door":1,"minecraft:shulker_box":87,"minecraft:flint_and_steel":1,"minecraft:suspicious_stew":1,"car:license_plate":1,"car:warped_body":1,"minecraft:shield":1,"minecraft:iron_chestplate":8,"minecraft:cake":2,"minecraft:oak_sapling":23,"minecraft:spruce_log":64,"minecraft:raw_gold":16,"minecraft:light_blue_bed":1},"minecraft:mined":{"securitycraft:mine":4,"create:deepslate_zinc_ore":8,"minecraft:oak_sapling":1,"minecraft:obsidian":4,"minecraft:granite":23,"minecraft:grass_block":30,"minecraft:soul_soil":3,"minecraft:deepslate_bricks":1,"minecraft:polished_diorite":5,"minecraft:iron_ore":18,"minecraft:cobbled_deepslate":1,"minecraft:fire":2,"minecraft:deepslate_lapis_ore":9,"create:asurine":20,"minecraft:white_shulker_box":2,"minecraft:deepslate_redstone_ore":56,"minecraft:brown_shulker_box":145,"minecraft:blackstone":1,"minecraft:torch":3,"minecraft:calcite":5,"minecraft:poppy":1,"minecraft:glass":1,"minecraft:nether_quartz_ore":74,"minecraft:cobblestone":13,"minecraft:wall_torch":1,"minecraft:birch_sapling":1,"minecraft:birch_log":363,"minecraft:wheat":648,"minecraft:grass":27,"minecraft:oak_log":1734,"minecraft:dirt":169,"minecraft:netherrack":94,"minecraft:oak_leaves":594,"minecraft:deepslate":1874,"create:zinc_ore":1,"minecraft:tuff":157,"minecraft:quartz_stairs":3,"minecraft:dark_oak_leaves":11,"minecraft:deepslate_diamond_ore":41,"minecraft:dark_oak_log":66,"minecraft:spruce_leaves":101,"minecraft:large_fern":2,"minecraft:hay_block":77,"minecraft:andesite":49,"minecraft:stripped_spruce_log":1,"minecraft:deepslate_iron_ore":16,"minecraft:stone":254,"minecraft:scaffolding":4,"minecraft:soul_sand":7,"minecraft:basalt":30,"minecraft:tall_grass":10,"minecraft:deepslate_gold_ore":73,"minecraft:diorite":8,"minecraft:light_blue_bed":1,"minecraft:spruce_log":327,"minecraft:birch_leaves":18,"minecraft:coal_ore":100,"minecraft:cocoa":139,"minecraft:gravel":18,"minecraft:stone_bricks":3,"minecraft:infested_stone":3},"minecraft:picked_up":{"minecraft:shulker_shell":61,"minecraft:iron_chestplate":10,"minecraft:wheat":637,"securitycraft:keypad_item":1,"car:wheel":4,"minecraft:suspicious_stew":2,"create:metal_bracket":4,"minecraft:lead":2,"minecraft:diamond_sword":1,"minecraft:potion":28,"minecraft:enchanted_book":4,"minecraft:string":98,"minecraft:soul_soil":3,"minecraft:cooked_salmon":1,"minecraft:iron_leggings":10,"minecraft:sticky_piston":3,"create:piston_extension_pole":2,"minecraft:blue_stained_glass_pane":1,"create:sticky_mechanical_piston":2,"minecraft:black_shulker_box":1,"minecraft:cobbled_deepslate":1362,"minecraft:bucket":1,"create:powered_toggle_latch":2,"minecraft:rose_bush":8,"minecraft:written_book":3,"minecraft:calcite":5,"minecraft:smooth_quartz":7,"minecraft:enchanted_golden_apple":1,"minecraft:coal_block":16,"minecraft:smooth_quartz_stairs":29,"minecraft:dark_oak_door":21,"minecraft:stick":178,"car:canola_cake":1,"create:netherite_diving_helmet":2,"minecraft:torch":4,"minecraft:netherite_shovel":1,"create:redstone_contact":1,"minecraft:diorite":8,"minecraft:cauldron":1,"minecraft:command_block":1,"create:clipboard":2,"securitycraft:harming_module":1,"create:track":4,"create:asurine":20,"minecraft:brown_shulker_box":261,"minecraft:carved_pumpkin":2,"minecraft:mangrove_door":1,"minecraft:spruce_hanging_sign":1,"minecraft:blaze_rod":1,"minecraft:obsidian":1,"create:linked_controller":1,"minecraft:cobblestone":298,"minecraft:birch_log":538,"minecraft:lilac":12,"minecraft:repeater":2,"car:key":2,"minecraft:water_bucket":6,"minecraft:andesite":46,"create:belt_connector":2,"minecraft:flint":12,"minecraft:tuff":155,"create:raw_zinc":15,"minecraft:netherite_leggings":2,"minecraft:lapis_lazuli":96,"minecraft:dirt":242,"minecraft:lantern":8,"locallooks:magic_mirror":3,"minecraft:glass":1,"minecraft:orange_tulip":1,"minecraft:wheat_seeds":1805,"minecraft:raw_gold":194,"minecraft:dark_oak_sign":8,"minecraft:netherite_axe":43,"car:canola":60,"create:netherite_diving_boots":2,"minecraft:prismarine":2,"minecraft:oak_planks":13,"securitycraft:mine":4,"car:canola_seeds":9,"minecraft:polished_blackstone_slab":1,"minecraft:black_stained_glass_pane":1,"minecraft:stripped_spruce_log":1,"minecraft:grass_block":2,"minecraft:lily_of_the_valley":19,"minecraft:diamond_block":4,"minecraft:dark_oak_log":66,"minecraft:shulker_box":105,"create:netherite_backtank":2,"minecraft:blue_terracotta":1,"minecraft:diamond":109,"minecraft:polished_blackstone_button":1,"webdisplays:minepad":39,"minecraft:writable_book":9,"minecraft:granite":25,"minecraft:white_concrete":5,"minecraft:spruce_button":1,"minecraft:spruce_sign":3,"create:framed_glass_door":4,"minecraft:oak_sapling":192,"minecraft:netherrack":89,"minecraft:chorus_fruit":6,"minecraft:oak_leaves":461,"minecraft:cocoa_beans":448,"securitycraft:redstone_module":10,"securitycraft:panic_button":3,"minecraft:wooden_pickaxe":1,"minecraft:cooked_rabbit":1,"minecraft:item_frame":39,"minecraft:white_carpet":8,"create:redstone_link":11,"minecraft:blackstone":2,"minecraft:glass_pane":9,"minecraft:netherite_sword":12,"minecraft:player_head":5,"securitycraft:smart_module":8,"minecraft:observer":1,"minecraft:poppy":48,"minecraft:spruce_slab":5,"minecraft:quartz_stairs":3,"minecraft:blue_shulker_box":1,"minecraft:chest":64,"minecraft:birch_sapling":85,"minecraft:spruce_trapdoor":1,"minecraft:egg":79,"minecraft:dark_oak_sapling":4,"minecraft:black_stained_glass":1,"minecraft:raw_iron":87,"minecraft:stone":1,"create:railway_casing":1,"minecraft:music_disc_relic":2,"minecraft:glow_item_frame":31,"minecraft:cake":6,"minecraft:stone_button":1,"minecraft:cookie":799,"minecraft:music_disc_11":142,"minecraft:trident":8,"minecraft:light_blue_bed":1,"minecraft:redstone":371,"minecraft:netherite_pickaxe":14,"securitycraft:alarm":5,"minecraft:peony":16,"minecraft:deepslate_bricks":1,"minecraft:hay_block":77,"minecraft:gold_ingot":30,"minecraft:polished_blackstone":2,"minecraft:white_shulker_box":9,"minecraft:mutton":2,"minecraft:white_wool":1,"easy_npc:move_easy_npc":6,"minecraft:birch_leaves":1,"minecraft:basalt":25,"minecraft:golden_carrot":1,"easy_npc:humanoid_spawn_egg":1,"minecraft:salmon":4,"securitycraft:disguise_module":1,"create:framed_glass_trapdoor":1,"minecraft:oak_log":3824,"framedblocks:framed_slab":1,"minecraft:paper":237,"minecraft:apple":67,"minecraft:stone_bricks":1,"securitycraft:projector":3,"securitycraft:security_camera":2,"minecraft:iron_ingot":109,"minecraft:cooked_chicken":1,"minecraft:glass_bottle":2,"minecraft:soul_sand":7,"minecraft:music_disc_chirp":2,"minecraft:scaffolding":10,"minecraft:polished_andesite_stairs":1,"car:light_blue_sport_body":1,"minecraft:milk_bucket":1,"minecraft:nether_quartz_ore":32,"minecraft:quartz":173,"minecraft:dandelion":18,"minecraft:gravel":3,"minecraft:soul_torch":1,"minecraft:spruce_sapling":16,"minecraft:spruce_log":389,"minecraft:sea_lantern":7,"create:creative_motor":7,"minecraft:lime_banner":2,"minecraft:dried_kelp_block":60,"minecraft:polished_diorite":3,"webdisplays:laserpointer":5,"webdisplays:craftcomp_laserdiode":2,"minecraft:chainmail_leggings":1,"minecraft:painting":4,"minecraft:birch_sign":1,"minecraft:oak_button":7,"securitycraft:door_indestructible_iron_item":2,"minecraft:smooth_quartz_slab":8,"minecraft:coal":210,"minecraft:wooden_axe":3}},"DataVersion":3465}